mypackage/__init__.py
mypackage/call_ga4_api.py
itwingstestsproject-0.1.dist-info/LICENSE
itwingstestsproject-0.1.dist-info/METADATA
itwingstestsproject-0.1.dist-info/WHEEL
itwingstestsproject-0.1.dist-info/top_level.txt
itwingstestsproject-0.1.dist-info/RECORD
